bfstyle
